pystega/__init__.py
pystega/pystega.py
pystega-0.1.dist-info/LICENSE
pystega-0.1.dist-info/METADATA
pystega-0.1.dist-info/WHEEL
pystega-0.1.dist-info/top_level.txt
pystega-0.1.dist-info/RECORD
